cua_client/__init__.py
cua_client/computer_use.py
cua_client/excel_reader.py
cua_client/file_upload.py
cua_client/logging_config.py
cua_client/main.py
cua_client/pdf_reader.py
cua_client/py.typed
cua_client/remote_function_client.py
cua_client/reset_windows.py
cua_client/send_keys.py
cua_client/word_reader.py
cua_client/capture/__init__.py
cua_client/capture/config.py
cua_client/capture/frame_grabber.py
cua_client/capture/image_batch_recorder.py
cua_client/capture/keylog.py
cua_client/capture/overlay.py
cua_client/capture/screen_capture_controller.py
cua_client/capture/work_item.py
cua_client/windows/README.md
cua_client/windows/cleanup_old_logs.ps1
cua_client/windows/reset_cua_client.ps1
cua_client/windows/setup_task_scheduler.ps1
cua_client-0.3.5.dist-info/licenses/LICENSE
cua_client-0.3.5.dist-info/METADATA
cua_client-0.3.5.dist-info/WHEEL
cua_client-0.3.5.dist-info/entry_points.txt
cua_client-0.3.5.dist-info/top_level.txt
cua_client-0.3.5.dist-info/RECORD
