Metadata-Version: 2.4
Name: cua-client
Version: 0.3.5
Summary: Computer Use Automation (CUA) client for remote function execution
Author-email: 168x Project <admin@168x.com>
Maintainer-email: 168x Project <admin@168x.com>
License-Expression: MIT
Project-URL: Homepage, https://github.com/168x/cua-client
Project-URL: Repository, https://github.com/168x/cua-client
Project-URL: Documentation, https://github.com/168x/cua-client#readme
Project-URL: Issues, https://github.com/168x/cua-client/issues
Keywords: automation,remote,computer-use,websocket,rpc
Classifier: Development Status :: 4 - Beta
Classifier: Intended Audience :: Developers
Classifier: Operating System :: OS Independent
Classifier: Programming Language :: Python :: 3
Classifier: Programming Language :: Python :: 3.8
Classifier: Programming Language :: Python :: 3.9
Classifier: Programming Language :: Python :: 3.10
Classifier: Programming Language :: Python :: 3.11
Classifier: Programming Language :: Python :: 3.12
Classifier: Topic :: Software Development :: Libraries :: Python Modules
Classifier: Topic :: System :: Distributed Computing
Classifier: Topic :: Internet :: WWW/HTTP :: Dynamic Content
Requires-Python: >=3.8
License-File: LICENSE
Requires-Dist: pydantic
Requires-Dist: websockets
Requires-Dist: pynput
Requires-Dist: Pillow
Requires-Dist: pyautogui
Requires-Dist: PyMuPDF
Requires-Dist: msvc-runtime
Requires-Dist: mss>=9.0.0
Requires-Dist: opencv-python-headless>=4.9.0
Requires-Dist: numpy>=1.23.0
Requires-Dist: requests>=2.31.0
Requires-Dist: pandas>=2.2.2
Requires-Dist: openpyxl>=3.1.2
Requires-Dist: xlrd>=2.0.1
Provides-Extra: dev
Requires-Dist: pytest>=6.0; extra == "dev"
Requires-Dist: pytest-asyncio>=0.18.0; extra == "dev"
Requires-Dist: black>=22.0; extra == "dev"
Requires-Dist: flake8>=4.0; extra == "dev"
Requires-Dist: mypy>=0.900; extra == "dev"
Dynamic: license-file
